more_sso/__init__.py
more_sso/cache.py
more_sso/config.py
more_sso/decorators.py
more_sso/exceptions.py
more_sso/permissions.py
more_sso/validator.py
moresso-1.2.2.dist-info/licenses/LICENSE
moresso-1.2.2.dist-info/METADATA
moresso-1.2.2.dist-info/WHEEL
moresso-1.2.2.dist-info/top_level.txt
moresso-1.2.2.dist-info/RECORD
