Metadata-Version: 2.4
Name: moresso
Version: 1.2.2
Summary: A lightweight and extensible Single Sign-On (SSO) authentication library for Python.
Author-email: chalapathy v <chalapathyv57@gmail.com>
License: MIT
Requires-Python: >=3.8
License-File: LICENSE
Dynamic: license-file
